CoverageCompacter/CoverageCompacter.py
CoverageCompacter/__init__.py
CoverageCompacter/test_CoverageCompacter.py
CoverageCompacter-1.0.dist-info/LICENCE.txt
CoverageCompacter-1.0.dist-info/METADATA
CoverageCompacter-1.0.dist-info/WHEEL
CoverageCompacter-1.0.dist-info/top_level.txt
CoverageCompacter-1.0.dist-info/RECORD
