Metadata-Version: 2.1
Name: CoverageCompacter
Version: 1.0
Summary: Package to extrapolate coverage estimates from ultra low sequenced genomes generated by whole genome amplification (WGA) based library preparation methods
Home-page: https://github.com/wes3985/CoverageCompacter
Author: Wes Woollard
Author-email: wes.woollard3985@gmail.com
License: MIT
Platform: UNKNOWN
